{"0": {"my-scheduler-6b748d4857-22kt6": {"setup time": 109.565012227, "avg time per iter": 273702.23076923075, "total time": 3558129, "total iter": 12, "msg rcv total": 46782, "msg sent total": 38438}, "my-scheduler-6b748d4857-29jx7": {"setup time": 114.991888814, "avg time per iter": 286585.6153846154, "total time": 3725613, "total iter": 12, "msg rcv total": 42560, "msg sent total": 39051}, "my-scheduler-6b748d4857-2bs8v": {"setup time": 107.000074708, "avg time per iter": 273404.46153846156, "total time": 3554258, "total iter": 12, "msg rcv total": 32544, "msg sent total": 36326}, "my-scheduler-6b748d4857-2jn85": {"setup time": 132.041021616, "avg time per iter": 290141.23076923075, "total time": 3771836, "total iter": 12, "msg rcv total": 39900, "msg sent total": 47083}, "my-scheduler-6b748d4857-2nb9q": {"setup time": 123.677389549, "avg time per iter": 288172.07692307694, "total time": 3746237, "total iter": 12, "msg rcv total": 43225, "msg sent total": 41085}, "my-scheduler-6b748d4857-2nh56": {"setup time": 121.98090649, "avg time per iter": 286966, "total time": 3730558, "total iter": 12, "msg rcv total": 36575, "msg sent total": 32962}, "my-scheduler-6b748d4857-2pz6z": {"setup time": 70.416596491, "avg time per iter": 275059.1538461539, "total time": 3575769, "total iter": 12, "msg rcv total": 44748, "msg sent total": 35100}, "my-scheduler-6b748d4857-2x466": {"setup time": 66.538503948, "avg time per iter": 282821.92307692306, "total time": 3676685, "total iter": 12, "msg rcv total": 37290, "msg sent total": 36378}, "my-scheduler-6b748d4857-2x95f": {"setup time": 119.50803929, "avg time per iter": 286370.23076923075, "total time": 3722813, "total iter": 12, "msg rcv total": 39900, "msg sent total": 41111}, "my-scheduler-6b748d4857-46zft": {"setup time": 87.841989562, "avg time per iter": 280510.8461538461, "total time": 3646641, "total iter": 12, "msg rcv total": 35934, "msg sent total": 41163}, "my-scheduler-6b748d4857-48zzf": {"setup time": 81.9087287, "avg time per iter": 277852, "total time": 3612076, "total iter": 12, "msg rcv total": 34578, "msg sent total": 40459}, "my-scheduler-6b748d4857-49nkg": {"setup time": 95.874137391, "avg time per iter": 275948.46153846156, "total time": 3587330, "total iter": 12, "msg rcv total": 48138, "msg sent total": 49834}, "my-scheduler-6b748d4857-4cwjm": {"setup time": 107.746509825, "avg time per iter": 283674.53846153844, "total time": 3687769, "total iter": 12, "msg rcv total": 43392, "msg sent total": 44449}, "my-scheduler-6b748d4857-4dsdt": {"setup time": 109.60324341, "avg time per iter": 285665.3076923077, "total time": 3713649, "total iter": 12, "msg rcv total": 39324, "msg sent total": 34296}, "my-scheduler-6b748d4857-4gsl2": {"setup time": 104.83065418, "avg time per iter": 279373.07692307694, "total time": 3631850, "total iter": 12, "msg rcv total": 47460, "msg sent total": 33027}, "my-scheduler-6b748d4857-4gvp9": {"setup time": 115.991834676, "avg time per iter": 286006.23076923075, "total time": 3718081, "total iter": 12, "msg rcv total": 43890, "msg sent total": 49078}, "my-scheduler-6b748d4857-4kd4w": {"setup time": 130.452407065, "avg time per iter": 289448, "total time": 3762824, "total iter": 12, "msg rcv total": 45220, "msg sent total": 38399}, "my-scheduler-6b748d4857-4lw6n": {"setup time": 84.885342134, "avg time per iter": 279494.1538461539, "total time": 3633424, "total iter": 12, "msg rcv total": 46104, "msg sent total": 43054}, "my-scheduler-6b748d4857-4v8v5": {"setup time": 105.069001354, "avg time per iter": 281703.53846153844, "total time": 3662146, "total iter": 12, "msg rcv total": 42036, "msg sent total": 49912}, "my-scheduler-6b748d4857-4xg59": {"setup time": 92.340506177, "avg time per iter": 277791.23076923075, "total time": 3611286, "total iter": 12, "msg rcv total": 44070, "msg sent total": 41059}, "my-scheduler-6b748d4857-59b5p": {"setup time": 93.139307164, "avg time per iter": 273484.23076923075, "total time": 3555295, "total iter": 12, "msg rcv total": 40680, "msg sent total": 43119}, "my-scheduler-6b748d4857-5gpw8": {"setup time": 79.031011545, "avg time per iter": 278566.6923076923, "total time": 3621367, "total iter": 12, "msg rcv total": 33222, "msg sent total": 45805}, "my-scheduler-6b748d4857-5ktdb": {"setup time": 85.464976244, "avg time per iter": 280828.53846153844, "total time": 3650771, "total iter": 12, "msg rcv total": 35256, "msg sent total": 44410}, "my-scheduler-6b748d4857-5l8x8": {"setup time": 81.182617537, "avg time per iter": 278308.53846153844, "total time": 3618011, "total iter": 12, "msg rcv total": 48138, "msg sent total": 35035}, "my-scheduler-6b748d4857-5pzxn": {"setup time": 78.71449289, "avg time per iter": 277326.6923076923, "total time": 3605247, "total iter": 12, "msg rcv total": 39324, "msg sent total": 26273}, "my-scheduler-6b748d4857-5qv6b": {"setup time": 95.307166889, "avg time per iter": 274478.92307692306, "total time": 3568226, "total iter": 12, "msg rcv total": 37968, "msg sent total": 44501}, "my-scheduler-6b748d4857-5rtvg": {"setup time": 82.307444765, "avg time per iter": 280649.46153846156, "total time": 3648443, "total iter": 12, "msg rcv total": 43392, "msg sent total": 51268}, "my-scheduler-6b748d4857-5s2fn": {"setup time": 112.348457834, "avg time per iter": 284559, "total time": 3699267, "total iter": 12, "msg rcv total": 34580, "msg sent total": 39794}, "my-scheduler-6b748d4857-5z276": {"setup time": 78.770979607, "avg time per iter": 278622.23076923075, "total time": 3622089, "total iter": 12, "msg rcv total": 42036, "msg sent total": 47148}, "my-scheduler-6b748d4857-64st4": {"setup time": 114.730083882, "avg time per iter": 287239.46153846156, "total time": 3734113, "total iter": 12, "msg rcv total": 35245, "msg sent total": 35648}, "my-scheduler-6b748d4857-658q6": {"setup time": 102.236032362, "avg time per iter": 278182.92307692306, "total time": 3616378, "total iter": 12, "msg rcv total": 35256, "msg sent total": 32988}, "my-scheduler-6b748d4857-66bpg": {"setup time": 96.719056737, "avg time per iter": 272041.76923076925, "total time": 3536543, "total iter": 12, "msg rcv total": 33222, "msg sent total": 28920}, "my-scheduler-6b748d4857-674wm": {"setup time": 67.91876811, "avg time per iter": 284367.8461538461, "total time": 3696782, "total iter": 12, "msg rcv total": 48816, "msg sent total": 46431}, "my-scheduler-6b748d4857-67cg5": {"setup time": 123.238980242, "avg time per iter": 288089.76923076925, "total time": 3745167, "total iter": 12, "msg rcv total": 43225, "msg sent total": 39820}, "my-scheduler-6b748d4857-6dgqd": {"setup time": 101.631690163, "avg time per iter": 277497.53846153844, "total time": 3607468, "total iter": 12, "msg rcv total": 40002, "msg sent total": 43775}, "my-scheduler-6b748d4857-6f96f": {"setup time": 114.221353835, "avg time per iter": 284803.6923076923, "total time": 3702448, "total iter": 12, "msg rcv total": 44555, "msg sent total": 37734}, "my-scheduler-6b748d4857-6j6h7": {"setup time": 95.408141372, "avg time per iter": 276247.53846153844, "total time": 3591218, "total iter": 12, "msg rcv total": 45426, "msg sent total": 38438}, "my-scheduler-6b748d4857-6jbmq": {"setup time": 75.701521827, "avg time per iter": 278300.76923076925, "total time": 3617910, "total iter": 12, "msg rcv total": 46104, "msg sent total": 37082}, "my-scheduler-6b748d4857-6km7p": {"setup time": 105.214141521, "avg time per iter": 282794.6153846154, "total time": 3676330, "total iter": 12, "msg rcv total": 46782, "msg sent total": 46435}, "my-scheduler-6b748d4857-6lzdm": {"setup time": 101.267255002, "avg time per iter": 277594.8461538461, "total time": 3608733, "total iter": 12, "msg rcv total": 40680, "msg sent total": 35648}, "my-scheduler-6b748d4857-6nmln": {"setup time": 80.259386743, "avg time per iter": 274849.76923076925, "total time": 3573047, "total iter": 12, "msg rcv total": 34578, "msg sent total": 42467}, "my-scheduler-6b748d4857-6pl2f": {"setup time": 125.822813888, "avg time per iter": 288466.07692307694, "total time": 3750059, "total iter": 12, "msg rcv total": 37240, "msg sent total": 49169}, "my-scheduler-6b748d4857-6qcbv": {"setup time": 75.6024459, "avg time per iter": 279897.23076923075, "total time": 3638664, "total iter": 12, "msg rcv total": 35256, "msg sent total": 45857}, "my-scheduler-6b748d4857-6qt4c": {"setup time": 97.830252417, "avg time per iter": 275280.3076923077, "total time": 3578644, "total iter": 12, "msg rcv total": 33900, "msg sent total": 37747}, "my-scheduler-6b748d4857-6sns4": {"setup time": 80.888316, "avg time per iter": 277468.07692307694, "total time": 3607085, "total iter": 12, "msg rcv total": 47460, "msg sent total": 36365}, "my-scheduler-6b748d4857-6tw7l": {"setup time": 129.581759779, "avg time per iter": 289660.6923076923, "total time": 3765589, "total iter": 12, "msg rcv total": 33915, "msg sent total": 43875}, "my-scheduler-6b748d4857-6v769": {"setup time": 129.597625837, "avg time per iter": 289537.8461538461, "total time": 3763992, "total iter": 12, "msg rcv total": 41230, "msg sent total": 43784}, "my-scheduler-6b748d4857-74lfq": {"setup time": 89.888686793, "avg time per iter": 282625.53846153844, "total time": 3674132, "total iter": 12, "msg rcv total": 37290, "msg sent total": 42989}, "my-scheduler-6b748d4857-74xj9": {"setup time": 119.643114225, "avg time per iter": 287392.46153846156, "total time": 3736102, "total iter": 12, "msg rcv total": 39900, "msg sent total": 40420}, "my-scheduler-6b748d4857-765hk": {"setup time": 120.348497056, "avg time per iter": 288087.6923076923, "total time": 3745140, "total iter": 12, "msg rcv total": 40565, "msg sent total": 46444}, "my-scheduler-6b748d4857-76qbg": {"setup time": 104.240082346, "avg time per iter": 281316.3076923077, "total time": 3657112, "total iter": 12, "msg rcv total": 46104, "msg sent total": 35752}, "my-scheduler-6b748d4857-784g5": {"setup time": 66.293954177, "avg time per iter": 283112.53846153844, "total time": 3680463, "total iter": 12, "msg rcv total": 38646, "msg sent total": 47243}, "my-scheduler-6b748d4857-78ksp": {"setup time": 99.326507648, "avg time per iter": 273461.8461538461, "total time": 3555004, "total iter": 12, "msg rcv total": 42714, "msg sent total": 43862}, "my-scheduler-6b748d4857-79zkp": {"setup time": 102.377212134, "avg time per iter": 279603.6153846154, "total time": 3634847, "total iter": 12, "msg rcv total": 38646, "msg sent total": 40420}, "my-scheduler-6b748d4857-7cr4r": {"setup time": 108.510099031, "avg time per iter": 283693.23076923075, "total time": 3688012, "total iter": 12, "msg rcv total": 45426, "msg sent total": 43927}, "my-scheduler-6b748d4857-7f2gn": {"setup time": 99.34719234, "avg time per iter": 274183.3076923077, "total time": 3564383, "total iter": 12, "msg rcv total": 42714, "msg sent total": 44488}, "my-scheduler-6b748d4857-7g75r": {"setup time": 97.765521541, "avg time per iter": 275934.46153846156, "total time": 3587148, "total iter": 12, "msg rcv total": 42714, "msg sent total": 37786}, "my-scheduler-6b748d4857-7gb6z": {"setup time": 117.63899037, "avg time per iter": 285028, "total time": 3705364, "total iter": 12, "msg rcv total": 45885, "msg sent total": 43149}, "my-scheduler-6b748d4857-7j6f5": {"setup time": 115.693378726, "avg time per iter": 284990.46153846156, "total time": 3704876, "total iter": 12, "msg rcv total": 31255, "msg sent total": 42363}, "my-scheduler-6b748d4857-7jw8p": {"setup time": 127.444403711, "avg time per iter": 288508.07692307694, "total time": 3750605, "total iter": 12, "msg rcv total": 40565, "msg sent total": 48517}, "my-scheduler-6b748d4857-7m6bl": {"setup time": 94.484058322, "avg time per iter": 275772.6923076923, "total time": 3585045, "total iter": 12, "msg rcv total": 41358, "msg sent total": 46457}, "my-scheduler-6b748d4857-7n2tc": {"setup time": 72.265838675, "avg time per iter": 277963, "total time": 3613519, "total iter": 12, "msg rcv total": 37290, "msg sent total": 37056}, "my-scheduler-6b748d4857-7nd74": {"setup time": 94.453086225, "avg time per iter": 275699.8461538461, "total time": 3584098, "total iter": 12, "msg rcv total": 44748, "msg sent total": 37734}, "my-scheduler-6b748d4857-7nfwc": {"setup time": 108.349094806, "avg time per iter": 284235.07692307694, "total time": 3695056, "total iter": 12, "msg rcv total": 42036, "msg sent total": 50529}, "my-scheduler-6b748d4857-7nz7r": {"setup time": 99.73848939, "avg time per iter": 274575.92307692306, "total time": 3569487, "total iter": 12, "msg rcv total": 40002, "msg sent total": 40446}, "my-scheduler-6b748d4857-7q99x": {"setup time": 65.072553264, "avg time per iter": 284010.6923076923, "total time": 3692139, "total iter": 12, "msg rcv total": 37968, "msg sent total": 41046}, "my-scheduler-6b748d4857-7tp2p": {"setup time": 134.610442393, "avg time per iter": 289422.1538461539, "total time": 3762488, "total iter": 12, "msg rcv total": 45885, "msg sent total": 41111}, "my-scheduler-6b748d4857-7v8qn": {"setup time": 99.050409064, "avg time per iter": 276629.6923076923, "total time": 3596186, "total iter": 12, "msg rcv total": 37290, "msg sent total": 41020}, "my-scheduler-6b748d4857-84fqs": {"setup time": 137.145002818, "avg time per iter": 289906, "total time": 3768778, "total iter": 12, "msg rcv total": 43225, "msg sent total": 35700}, "my-scheduler-6b748d4857-8bp82": {"setup time": 109.758553516, "avg time per iter": 285157, "total time": 3707041, "total iter": 12, "msg rcv total": 47460, "msg sent total": 35087}, "my-scheduler-6b748d4857-8fhxn": {"setup time": 98.047690844, "avg time per iter": 275391.07692307694, "total time": 3580084, "total iter": 12, "msg rcv total": 31866, "msg sent total": 48491}, "my-scheduler-6b748d4857-8frx4": {"setup time": 76.374050037, "avg time per iter": 279921.8461538461, "total time": 3638984, "total iter": 12, "msg rcv total": 31188, "msg sent total": 30315}, "my-scheduler-6b748d4857-8gv2r": {"setup time": 107.648050268, "avg time per iter": 271827.07692307694, "total time": 3533752, "total iter": 12, "msg rcv total": 45426, "msg sent total": 37056}, "my-scheduler-6b748d4857-8kwjb": {"setup time": 101.138294973, "avg time per iter": 277763.6923076923, "total time": 3610928, "total iter": 12, "msg rcv total": 44748, "msg sent total": 35691}, "my-scheduler-6b748d4857-8pndp": {"setup time": 130.866093022, "avg time per iter": 289890.6153846154, "total time": 3768578, "total iter": 12, "msg rcv total": 41895, "msg sent total": 32336}, "my-scheduler-6b748d4857-8qtl6": {"setup time": 97.259435482, "avg time per iter": 274652.3076923077, "total time": 3570480, "total iter": 12, "msg rcv total": 35256, "msg sent total": 37721}, "my-scheduler-6b748d4857-8qv4p": {"setup time": 98.596506833, "avg time per iter": 277400.46153846156, "total time": 3606206, "total iter": 12, "msg rcv total": 39324, "msg sent total": 40420}, "my-scheduler-6b748d4857-94v2j": {"setup time": 68.260328954, "avg time per iter": 283443.3846153846, "total time": 3684764, "total iter": 12, "msg rcv total": 44070, "msg sent total": 34996}, "my-scheduler-6b748d4857-96jmj": {"setup time": 81.309007078, "avg time per iter": 280222.92307692306, "total time": 3642898, "total iter": 12, "msg rcv total": 42714, "msg sent total": 45127}, "my-scheduler-6b748d4857-96psw": {"setup time": 80.114663137, "avg time per iter": 277967.6153846154, "total time": 3613579, "total iter": 12, "msg rcv total": 42714, "msg sent total": 41154}, "my-scheduler-6b748d4857-96v7w": {"setup time": 89.079299617, "avg time per iter": 282173.3846153846, "total time": 3668254, "total iter": 12, "msg rcv total": 33222, "msg sent total": 41072}, "my-scheduler-6b748d4857-97h8w": {"setup time": 108.295897698, "avg time per iter": 272858.92307692306, "total time": 3547166, "total iter": 12, "msg rcv total": 40680, "msg sent total": 34253}, "my-scheduler-6b748d4857-97j64": {"setup time": 90.555457637, "avg time per iter": 277139.8461538461, "total time": 3602818, "total iter": 12, "msg rcv total": 35256, "msg sent total": 40433}, "my-scheduler-6b748d4857-98h7g": {"setup time": 107.065577594, "avg time per iter": 283326.3076923077, "total time": 3683242, "total iter": 12, "msg rcv total": 44070, "msg sent total": 45818}, "my-scheduler-6b748d4857-99g5j": {"setup time": 85.244333099, "avg time per iter": 278877.3076923077, "total time": 3625405, "total iter": 12, "msg rcv total": 39324, "msg sent total": 41711}, "my-scheduler-6b748d4857-9c75w": {"setup time": 103.770854353, "avg time per iter": 280654.3846153846, "total time": 3648507, "total iter": 12, "msg rcv total": 39324, "msg sent total": 43054}, "my-scheduler-6b748d4857-9c79x": {"setup time": 83.956589067, "avg time per iter": 278930.76923076925, "total time": 3626100, "total iter": 12, "msg rcv total": 42714, "msg sent total": 44414}, "my-scheduler-6b748d4857-9chl8": {"setup time": 83.893310678, "avg time per iter": 277156.3076923077, "total time": 3603032, "total iter": 12, "msg rcv total": 37968, "msg sent total": 35674}, "my-scheduler-6b748d4857-9ddx8": {"setup time": 94.048680288, "avg time per iter": 274369.6923076923, "total time": 3566806, "total iter": 12, "msg rcv total": 40680, "msg sent total": 41098}, "my-scheduler-6b748d4857-9fpdv": {"setup time": 71.67523228, "avg time per iter": 275104.8461538461, "total time": 3576363, "total iter": 12, "msg rcv total": 46104, "msg sent total": 48569}, "my-scheduler-6b748d4857-9gvtt": {"setup time": 116.264728136, "avg time per iter": 285328.3846153846, "total time": 3709269, "total iter": 12, "msg rcv total": 46550, "msg sent total": 37021}, "my-scheduler-6b748d4857-9hc77": {"setup time": 83.432895291, "avg time per iter": 278293.6923076923, "total time": 3617818, "total iter": 12, "msg rcv total": 46104, "msg sent total": 38373}, "my-scheduler-6b748d4857-9hggp": {"setup time": 81.448697129, "avg time per iter": 277877.3846153846, "total time": 3612406, "total iter": 12, "msg rcv total": 47460, "msg sent total": 45153}, "my-scheduler-6b748d4857-9lrdz": {"setup time": 127.390323368, "avg time per iter": 289852.46153846156, "total time": 3768082, "total iter": 12, "msg rcv total": 43225, "msg sent total": 39690}, "my-scheduler-6b748d4857-9pzvm": {"setup time": 86.623431743, "avg time per iter": 280977, "total time": 3652701, "total iter": 12, "msg rcv total": 44748, "msg sent total": 34957}, "my-scheduler-6b748d4857-9tvx5": {"setup time": 107.227100661, "avg time per iter": 275126.6923076923, "total time": 3576647, "total iter": 12, "msg rcv total": 37290, "msg sent total": 37043}, "my-scheduler-6b748d4857-9v9xj": {"setup time": 116.285113571, "avg time per iter": 286948.07692307694, "total time": 3730325, "total iter": 12, "msg rcv total": 42560, "msg sent total": 41046}, "my-scheduler-6b748d4857-9vrkg": {"setup time": 85.322998977, "avg time per iter": 279820.1538461539, "total time": 3637662, "total iter": 12, "msg rcv total": 42036, "msg sent total": 36382}, "my-scheduler-6b748d4857-9wxhn": {"setup time": 73.536385487, "avg time per iter": 278081.3846153846, "total time": 3615058, "total iter": 12, "msg rcv total": 40680, "msg sent total": 45049}, "my-scheduler-6b748d4857-9x9h6": {"setup time": 131.829839774, "avg time per iter": 289364.8461538461, "total time": 3761743, "total iter": 12, "msg rcv total": 43225, "msg sent total": 35778}, "my-scheduler-6b748d4857-9x9pb": {"setup time": 131.378231374, "avg time per iter": 288956.92307692306, "total time": 3756440, "total iter": 12, "msg rcv total": 32585, "msg sent total": 45270}, "my-scheduler-6b748d4857-9xp4j": {"setup time": 127.250933003, "avg time per iter": 288248.3076923077, "total time": 3747228, "total iter": 12, "msg rcv total": 39900, "msg sent total": 35739}, "my-scheduler-6b748d4857-b5sx6": {"setup time": 79.657128, "avg time per iter": 277514.53846153844, "total time": 3607689, "total iter": 12, "msg rcv total": 38646, "msg sent total": 42480}, "my-scheduler-6b748d4857-b5wsm": {"setup time": 124.574748066, "avg time per iter": 288240, "total time": 3747120, "total iter": 12, "msg rcv total": 33250, "msg sent total": 44440}, "my-scheduler-6b748d4857-bcxgh": {"setup time": 74.809013317, "avg time per iter": 278836.6923076923, "total time": 3624877, "total iter": 12, "msg rcv total": 33900, "msg sent total": 41046}, "my-scheduler-6b748d4857-bgbqx": {"setup time": 89.930799945, "avg time per iter": 282211.3846153846, "total time": 3668748, "total iter": 12, "msg rcv total": 50172, "msg sent total": 33053}, "my-scheduler-6b748d4857-bgn52": {"setup time": 85.285111913, "avg time per iter": 276829.6923076923, "total time": 3598786, "total iter": 12, "msg rcv total": 49494, "msg sent total": 39168}, "my-scheduler-6b748d4857-bhjwv": {"setup time": 86.102335481, "avg time per iter": 277057.1538461539, "total time": 3601743, "total iter": 12, "msg rcv total": 42714, "msg sent total": 39038}, "my-scheduler-6b748d4857-bjxhv": {"setup time": 77.48617263, "avg time per iter": 276879.46153846156, "total time": 3599433, "total iter": 12, "msg rcv total": 39324, "msg sent total": 41776}, "my-scheduler-6b748d4857-bkgqr": {"setup time": 74.259687094, "avg time per iter": 276990.23076923075, "total time": 3600873, "total iter": 12, "msg rcv total": 37968, "msg sent total": 51177}, "my-scheduler-6b748d4857-bkjds": {"setup time": 82.292153416, "avg time per iter": 280024.76923076925, "total time": 3640322, "total iter": 12, "msg rcv total": 36612, "msg sent total": 28307}, "my-scheduler-6b748d4857-bkmll": {"setup time": 113.378049134, "avg time per iter": 284952.1538461539, "total time": 3704378, "total iter": 12, "msg rcv total": 40565, "msg sent total": 39729}, "my-scheduler-6b748d4857-bqmmx": {"setup time": 125.724127513, "avg time per iter": 288460.3076923077, "total time": 3749984, "total iter": 12, "msg rcv total": 32585, "msg sent total": 44436}, "my-scheduler-6b748d4857-br276": {"setup time": 104.460035047, "avg time per iter": 281530.1538461539, "total time": 3659892, "total iter": 12, "msg rcv total": 42714, "msg sent total": 37069}, "my-scheduler-6b748d4857-brfqj": {"setup time": 84.976003632, "avg time per iter": 279573.6153846154, "total time": 3634457, "total iter": 12, "msg rcv total": 33900, "msg sent total": 45844}, "my-scheduler-6b748d4857-btfvh": {"setup time": 80.52879558, "avg time per iter": 277692.07692307694, "total time": 3609997, "total iter": 12, "msg rcv total": 42714, "msg sent total": 38412}, "my-scheduler-6b748d4857-bv84q": {"setup time": 131.389838675, "avg time per iter": 290895.8461538461, "total time": 3781646, "total iter": 12, "msg rcv total": 36575, "msg sent total": 47813}, "my-scheduler-6b748d4857-bwdkv": {"setup time": 90.48978371, "avg time per iter": 275423.6153846154, "total time": 3580507, "total iter": 12, "msg rcv total": 43392, "msg sent total": 45205}, "my-scheduler-6b748d4857-bxbc8": {"setup time": 71.63420664, "avg time per iter": 275547.76923076925, "total time": 3582121, "total iter": 12, "msg rcv total": 41358, "msg sent total": 33644}, "my-scheduler-6b748d4857-c4dlp": {"setup time": 78.49353275, "avg time per iter": 281204.23076923075, "total time": 3655655, "total iter": 12, "msg rcv total": 37968, "msg sent total": 35726}, "my-scheduler-6b748d4857-c5vr9": {"setup time": 79.532192195, "avg time per iter": 277937.53846153844, "total time": 3613188, "total iter": 12, "msg rcv total": 42036, "msg sent total": 37056}, "my-scheduler-6b748d4857-c82fm": {"setup time": 130.854663878, "avg time per iter": 290315.3846153846, "total time": 3774100, "total iter": 12, "msg rcv total": 35910, "msg sent total": 43093}, "my-scheduler-6b748d4857-cblfs": {"setup time": 95.632608843, "avg time per iter": 274399.53846153844, "total time": 3567194, "total iter": 12, "msg rcv total": 37968, "msg sent total": 37056}, "my-scheduler-6b748d4857-ccqvg": {"setup time": 103.567792057, "avg time per iter": 279849, "total time": 3638037, "total iter": 12, "msg rcv total": 44748, "msg sent total": 41676}, "my-scheduler-6b748d4857-cd4tz": {"setup time": 113.095004427, "avg time per iter": 285059.6923076923, "total time": 3705776, "total iter": 12, "msg rcv total": 37905, "msg sent total": 35061}, "my-scheduler-6b748d4857-cdqkd": {"setup time": 120.385179043, "avg time per iter": 288462.8461538461, "total time": 3750017, "total iter": 12, "msg rcv total": 35245, "msg sent total": 43853}, "my-scheduler-6b748d4857-cfnjc": {"setup time": 73.051735775, "avg time per iter": 274073.6923076923, "total time": 3562958, "total iter": 12, "msg rcv total": 35256, "msg sent total": 39064}, "my-scheduler-6b748d4857-cghv4": {"setup time": 122.503577146, "avg time per iter": 288485.6923076923, "total time": 3750314, "total iter": 12, "msg rcv total": 38570, "msg sent total": 37760}, "my-scheduler-6b748d4857-chxx5": {"setup time": 126.899280862, "avg time per iter": 288667.3846153846, "total time": 3752676, "total iter": 12, "msg rcv total": 39900, "msg sent total": 42467}, "my-scheduler-6b748d4857-cjm5r": {"setup time": 119.396727305, "avg time per iter": 287922.53846153844, "total time": 3742993, "total iter": 12, "msg rcv total": 40565, "msg sent total": 35035}, "my-scheduler-6b748d4857-ck6sz": {"setup time": 111.22289042, "avg time per iter": 283973.6153846154, "total time": 3691657, "total iter": 12, "msg rcv total": 48138, "msg sent total": 38373}, "my-scheduler-6b748d4857-cl5xd": {"setup time": 86.565219138, "avg time per iter": 281815.76923076925, "total time": 3663605, "total iter": 12, "msg rcv total": 44748, "msg sent total": 34318}, "my-scheduler-6b748d4857-cpbtr": {"setup time": 121.78384058, "avg time per iter": 289825.8461538461, "total time": 3767736, "total iter": 12, "msg rcv total": 36575, "msg sent total": 48556}, "my-scheduler-6b748d4857-cqjcg": {"setup time": 122.856092663, "avg time per iter": 288276, "total time": 3747588, "total iter": 12, "msg rcv total": 47880, "msg sent total": 37082}, "my-scheduler-6b748d4857-ct5x5": {"setup time": 97.905792285, "avg time per iter": 276466, "total time": 3594058, "total iter": 12, "msg rcv total": 36612, "msg sent total": 41098}, "my-scheduler-6b748d4857-cwz5x": {"setup time": 87.42028611, "avg time per iter": 281729.3076923077, "total time": 3662481, "total iter": 12, "msg rcv total": 36612, "msg sent total": 31645}, "my-scheduler-6b748d4857-czvvs": {"setup time": 131.386807031, "avg time per iter": 289181.6923076923, "total time": 3759362, "total iter": 12, "msg rcv total": 42560, "msg sent total": 39077}, "my-scheduler-6b748d4857-d2dnb": {"setup time": 114.519742779, "avg time per iter": 285937.53846153844, "total time": 3717188, "total iter": 12, "msg rcv total": 44555, "msg sent total": 39129}, "my-scheduler-6b748d4857-dc4pc": {"setup time": 114.005428533, "avg time per iter": 284347.8461538461, "total time": 3696522, "total iter": 12, "msg rcv total": 35245, "msg sent total": 40355}, "my-scheduler-6b748d4857-dj6bp": {"setup time": 111.067336773, "avg time per iter": 285485.8461538461, "total time": 3711316, "total iter": 12, "msg rcv total": 42714, "msg sent total": 52520}, "my-scheduler-6b748d4857-dk4pv": {"setup time": 121.782466242, "avg time per iter": 288538.6153846154, "total time": 3751002, "total iter": 12, "msg rcv total": 33915, "msg sent total": 37082}, "my-scheduler-6b748d4857-dmzjd": {"setup time": 127.855926024, "avg time per iter": 289017.6923076923, "total time": 3757230, "total iter": 12, "msg rcv total": 37240, "msg sent total": 39077}, "my-scheduler-6b748d4857-dmzrt": {"setup time": 102.400094847, "avg time per iter": 280170.07692307694, "total time": 3642211, "total iter": 12, "msg rcv total": 35934, "msg sent total": 40381}, "my-scheduler-6b748d4857-dp2fb": {"setup time": 105.880066681, "avg time per iter": 275748.53846153844, "total time": 3584731, "total iter": 12, "msg rcv total": 45426, "msg sent total": 39820}, "my-scheduler-6b748d4857-dqpnv": {"setup time": 87.369871903, "avg time per iter": 278137, "total time": 3615781, "total iter": 12, "msg rcv total": 33222, "msg sent total": 40433}, "my-scheduler-6b748d4857-drv52": {"setup time": 120.719439402, "avg time per iter": 288217.23076923075, "total time": 3746824, "total iter": 12, "msg rcv total": 45220, "msg sent total": 37669}, "my-scheduler-6b748d4857-dwbwp": {"setup time": 98.508965175, "avg time per iter": 277370.46153846156, "total time": 3605816, "total iter": 12, "msg rcv total": 34578, "msg sent total": 45270}, "my-scheduler-6b748d4857-dz59z": {"setup time": 103.943540711, "avg time per iter": 281537.23076923075, "total time": 3659984, "total iter": 12, "msg rcv total": 46782, "msg sent total": 43719}, "my-scheduler-6b748d4857-f2ht7": {"setup time": 99.378380358, "avg time per iter": 272797.8461538461, "total time": 3546372, "total iter": 12, "msg rcv total": 31866, "msg sent total": 33679}, "my-scheduler-6b748d4857-f2vzf": {"setup time": 127.699924122, "avg time per iter": 289109.6923076923, "total time": 3758426, "total iter": 12, "msg rcv total": 36575, "msg sent total": 41750}, "my-scheduler-6b748d4857-f2w2s": {"setup time": 111.64667681, "avg time per iter": 283064.6923076923, "total time": 3679841, "total iter": 12, "msg rcv total": 38646, "msg sent total": 40381}, "my-scheduler-6b748d4857-f6882": {"setup time": 85.271461404, "avg time per iter": 279214.76923076925, "total time": 3629792, "total iter": 12, "msg rcv total": 42036, "msg sent total": 39781}, "my-scheduler-6b748d4857-f6css": {"setup time": 126.205812062, "avg time per iter": 287581.3076923077, "total time": 3738557, "total iter": 12, "msg rcv total": 42560, "msg sent total": 33018}, "my-scheduler-6b748d4857-f6hk2": {"setup time": 119.153877543, "avg time per iter": 286302.6923076923, "total time": 3721935, "total iter": 12, "msg rcv total": 39900, "msg sent total": 41867}, "my-scheduler-6b748d4857-fccks": {"setup time": 74.356166525, "avg time per iter": 278655.46153846156, "total time": 3622521, "total iter": 12, "msg rcv total": 37290, "msg sent total": 37695}, "my-scheduler-6b748d4857-fczcp": {"setup time": 127.921844572, "avg time per iter": 287890.53846153844, "total time": 3742577, "total iter": 12, "msg rcv total": 49210, "msg sent total": 38334}, "my-scheduler-6b748d4857-fkcm9": {"setup time": 125.59540758, "avg time per iter": 289019.1538461539, "total time": 3757249, "total iter": 12, "msg rcv total": 39235, "msg sent total": 41802}, "my-scheduler-6b748d4857-fm7sd": {"setup time": 117.7879132, "avg time per iter": 285994.07692307694, "total time": 3717923, "total iter": 12, "msg rcv total": 43225, "msg sent total": 44488}, "my-scheduler-6b748d4857-fpj2l": {"setup time": 123.672611014, "avg time per iter": 286775.92307692306, "total time": 3728087, "total iter": 12, "msg rcv total": 29925, "msg sent total": 30263}, "my-scheduler-6b748d4857-fpn8x": {"setup time": 119.8913994, "avg time per iter": 286043.07692307694, "total time": 3718560, "total iter": 12, "msg rcv total": 33250, "msg sent total": 31723}, "my-scheduler-6b748d4857-fr7rq": {"setup time": 80.006218158, "avg time per iter": 279636.8461538461, "total time": 3635279, "total iter": 12, "msg rcv total": 37968, "msg sent total": 43145}, "my-scheduler-6b748d4857-fs2dn": {"setup time": 130.834949695, "avg time per iter": 290174, "total time": 3772262, "total iter": 12, "msg rcv total": 39235, "msg sent total": 43810}, "my-scheduler-6b748d4857-ft25j": {"setup time": 94.817525599, "avg time per iter": 275036, "total time": 3575468, "total iter": 12, "msg rcv total": 42036, "msg sent total": 40385}, "my-scheduler-6b748d4857-fv9mc": {"setup time": 94.010940542, "avg time per iter": 274538.23076923075, "total time": 3568997, "total iter": 12, "msg rcv total": 46104, "msg sent total": 32897}, "my-scheduler-6b748d4857-fxqdv": {"setup time": 122.674888008, "avg time per iter": 288251.1538461539, "total time": 3747265, "total iter": 12, "msg rcv total": 41895, "msg sent total": 37721}, "my-scheduler-6b748d4857-fznp2": {"setup time": 109.659248206, "avg time per iter": 284756.46153846156, "total time": 3701834, "total iter": 12, "msg rcv total": 35256, "msg sent total": 48517}, "my-scheduler-6b748d4857-g262t": {"setup time": 93.828981321, "avg time per iter": 272300.92307692306, "total time": 3539912, "total iter": 12, "msg rcv total": 37968, "msg sent total": 38334}, "my-scheduler-6b748d4857-g4qlr": {"setup time": 77.14432509, "avg time per iter": 280284.1538461539, "total time": 3643694, "total iter": 12, "msg rcv total": 29436, "msg sent total": 34996}, "my-scheduler-6b748d4857-g5s4f": {"setup time": 97.188880423, "avg time per iter": 276193.76923076925, "total time": 3590519, "total iter": 12, "msg rcv total": 41358, "msg sent total": 35726}, "my-scheduler-6b748d4857-g96ct": {"setup time": 89.692265938, "avg time per iter": 282754.6923076923, "total time": 3675811, "total iter": 12, "msg rcv total": 37968, "msg sent total": 49221}, "my-scheduler-6b748d4857-g9btx": {"setup time": 106.307109115, "avg time per iter": 282707.92307692306, "total time": 3675203, "total iter": 12, "msg rcv total": 40002, "msg sent total": 42441}, "my-scheduler-6b748d4857-g9p89": {"setup time": 90.564374634, "avg time per iter": 277625.1538461539, "total time": 3609127, "total iter": 12, "msg rcv total": 43392, "msg sent total": 39103}, "my-scheduler-6b748d4857-gdsq6": {"setup time": 104.539439424, "avg time per iter": 274574.76923076925, "total time": 3569472, "total iter": 12, "msg rcv total": 35256, "msg sent total": 42519}, "my-scheduler-6b748d4857-gncr8": {"setup time": 120.051104203, "avg time per iter": 288197.46153846156, "total time": 3746567, "total iter": 12, "msg rcv total": 40565, "msg sent total": 43145}, "my-scheduler-6b748d4857-grjrs": {"setup time": 116.968047191, "avg time per iter": 287111.92307692306, "total time": 3732455, "total iter": 12, "msg rcv total": 32585, "msg sent total": 39768}, "my-scheduler-6b748d4857-gt6kk": {"setup time": 130.33861639, "avg time per iter": 289352.6923076923, "total time": 3761585, "total iter": 12, "msg rcv total": 51205, "msg sent total": 33692}, "my-scheduler-6b748d4857-gttq4": {"setup time": 111.192990237, "avg time per iter": 284917.8461538461, "total time": 3703932, "total iter": 12, "msg rcv total": 35934, "msg sent total": 44358}, "my-scheduler-6b748d4857-gtxbq": {"setup time": 108.573997852, "avg time per iter": 274416.53846153844, "total time": 3567415, "total iter": 12, "msg rcv total": 38646, "msg sent total": 42389}, "my-scheduler-6b748d4857-h2b4t": {"setup time": 89.246542682, "avg time per iter": 281800.8461538461, "total time": 3663411, "total iter": 12, "msg rcv total": 46104, "msg sent total": 37030}, "my-scheduler-6b748d4857-h2qlh": {"setup time": 114.318054624, "avg time per iter": 285792.3846153846, "total time": 3715301, "total iter": 12, "msg rcv total": 49875, "msg sent total": 37747}, "my-scheduler-6b748d4857-h4pxd": {"setup time": 113.788299246, "avg time per iter": 284707.53846153844, "total time": 3701198, "total iter": 12, "msg rcv total": 41230, "msg sent total": 44410}, "my-scheduler-6b748d4857-h4zgv": {"setup time": 91.774355219, "avg time per iter": 278216.1538461539, "total time": 3616810, "total iter": 12, "msg rcv total": 44748, "msg sent total": 37069}, "my-scheduler-6b748d4857-h55kf": {"setup time": 90.510789595, "avg time per iter": 277522.3076923077, "total time": 3607790, "total iter": 12, "msg rcv total": 42714, "msg sent total": 36391}, "my-scheduler-6b748d4857-h7sgb": {"setup time": 106.457553186, "avg time per iter": 274862.1538461539, "total time": 3573208, "total iter": 12, "msg rcv total": 44070, "msg sent total": 36378}, "my-scheduler-6b748d4857-hcsrj": {"setup time": 110.836356646, "avg time per iter": 285123.53846153844, "total time": 3706606, "total iter": 12, "msg rcv total": 42036, "msg sent total": 47943}, "my-scheduler-6b748d4857-hdgtz": {"setup time": 102.338259651, "avg time per iter": 273365.6923076923, "total time": 3553754, "total iter": 12, "msg rcv total": 44748, "msg sent total": 38464}, "my-scheduler-6b748d4857-hdtpg": {"setup time": 128.74163884, "avg time per iter": 290239.46153846156, "total time": 3773113, "total iter": 12, "msg rcv total": 41230, "msg sent total": 40368}, "my-scheduler-6b748d4857-hg47m": {"setup time": 106.841623049, "avg time per iter": 282338, "total time": 3670394, "total iter": 12, "msg rcv total": 40680, "msg sent total": 40394}, "my-scheduler-6b748d4857-hg8k8": {"setup time": 136.062021741, "avg time per iter": 289612.1538461539, "total time": 3764958, "total iter": 12, "msg rcv total": 45885, "msg sent total": 45127}, "my-scheduler-6b748d4857-hl7j5": {"setup time": 106.275078365, "avg time per iter": 281792.07692307694, "total time": 3663297, "total iter": 12, "msg rcv total": 37968, "msg sent total": 44492}, "my-scheduler-6b748d4857-hl8gz": {"setup time": 67.591795493, "avg time per iter": 282852, "total time": 3677076, "total iter": 12, "msg rcv total": 39324, "msg sent total": 43849}, "my-scheduler-6b748d4857-hlwvg": {"setup time": 122.474615028, "avg time per iter": 288974.3846153846, "total time": 3756667, "total iter": 12, "msg rcv total": 41895, "msg sent total": 40420}, "my-scheduler-6b748d4857-hmb9d": {"setup time": 132.190606991, "avg time per iter": 291224.53846153844, "total time": 3785919, "total iter": 12, "msg rcv total": 34580, "msg sent total": 47200}, "my-scheduler-6b748d4857-hpfmb": {"setup time": 109.980412381, "avg time per iter": 273258.46153846156, "total time": 3552360, "total iter": 12, "msg rcv total": 36612, "msg sent total": 39081}, "my-scheduler-6b748d4857-ht7hs": {"setup time": 110.418028198, "avg time per iter": 284513.1538461539, "total time": 3698671, "total iter": 12, "msg rcv total": 27120, "msg sent total": 35035}, "my-scheduler-6b748d4857-htfmj": {"setup time": 128.753100262, "avg time per iter": 288899.3076923077, "total time": 3755691, "total iter": 12, "msg rcv total": 41230, "msg sent total": 37030}, "my-scheduler-6b748d4857-j2hth": {"setup time": 122.848048711, "avg time per iter": 288527.6923076923, "total time": 3750860, "total iter": 12, "msg rcv total": 41230, "msg sent total": 39755}, "my-scheduler-6b748d4857-j49h5": {"setup time": 89.178773545, "avg time per iter": 281215.3076923077, "total time": 3655799, "total iter": 12, "msg rcv total": 38646, "msg sent total": 37764}, "my-scheduler-6b748d4857-j4c88": {"setup time": 80.515028963, "avg time per iter": 280222.53846153844, "total time": 3642893, "total iter": 12, "msg rcv total": 31188, "msg sent total": 39038}, "my-scheduler-6b748d4857-j5ftp": {"setup time": 130.298043302, "avg time per iter": 289421, "total time": 3762473, "total iter": 12, "msg rcv total": 46550, "msg sent total": 41137}, "my-scheduler-6b748d4857-j5j5q": {"setup time": 125.979651398, "avg time per iter": 289086.6153846154, "total time": 3758126, "total iter": 12, "msg rcv total": 42560, "msg sent total": 41776}, "my-scheduler-6b748d4857-j5zwv": {"setup time": 77.63389167, "avg time per iter": 277058.8461538461, "total time": 3601765, "total iter": 12, "msg rcv total": 52206, "msg sent total": 43810}, "my-scheduler-6b748d4857-j6ctn": {"setup time": 99.74826488, "avg time per iter": 278190.46153846156, "total time": 3616476, "total iter": 12, "msg rcv total": 37290, "msg sent total": 35739}, "my-scheduler-6b748d4857-jdp8v": {"setup time": 122.83114262, "avg time per iter": 287220.3076923077, "total time": 3733864, "total iter": 12, "msg rcv total": 32585, "msg sent total": 35739}, "my-scheduler-6b748d4857-jg66b": {"setup time": 117.270626718, "avg time per iter": 286898.6153846154, "total time": 3729682, "total iter": 12, "msg rcv total": 43225, "msg sent total": 34957}, "my-scheduler-6b748d4857-jh4ml": {"setup time": 103.862227799, "avg time per iter": 280147.8461538461, "total time": 3641922, "total iter": 12, "msg rcv total": 46782, "msg sent total": 40485}, "my-scheduler-6b748d4857-jpb2g": {"setup time": 82.786901564, "avg time per iter": 277931.46153846156, "total time": 3613109, "total iter": 12, "msg rcv total": 43392, "msg sent total": 35700}, "my-scheduler-6b748d4857-jrxqw": {"setup time": 95.787078477, "avg time per iter": 275015.1538461539, "total time": 3575197, "total iter": 12, "msg rcv total": 39324, "msg sent total": 41137}, "my-scheduler-6b748d4857-jssq5": {"setup time": 86.688833969, "avg time per iter": 277448.07692307694, "total time": 3606825, "total iter": 12, "msg rcv total": 40002, "msg sent total": 41098}, "my-scheduler-6b748d4857-jtw7g": {"setup time": 88.804796613, "avg time per iter": 277986.6153846154, "total time": 3613826, "total iter": 12, "msg rcv total": 39324, "msg sent total": 35739}, "my-scheduler-6b748d4857-jvj6q": {"setup time": 114.975416899, "avg time per iter": 285336.6153846154, "total time": 3709376, "total iter": 12, "msg rcv total": 41895, "msg sent total": 53328}, "my-scheduler-6b748d4857-jxh92": {"setup time": 73.678848304, "avg time per iter": 276440.46153846156, "total time": 3593726, "total iter": 12, "msg rcv total": 38646, "msg sent total": 45714}, "my-scheduler-6b748d4857-k9j6s": {"setup time": 129.14199062, "avg time per iter": 289248.07692307694, "total time": 3760225, "total iter": 12, "msg rcv total": 47215, "msg sent total": 34348}, "my-scheduler-6b748d4857-kc8pp": {"setup time": 98.353299809, "avg time per iter": 277528.53846153844, "total time": 3607871, "total iter": 12, "msg rcv total": 37968, "msg sent total": 54597}, "my-scheduler-6b748d4857-kfc9n": {"setup time": 138.572704522, "avg time per iter": 289838.76923076925, "total time": 3767904, "total iter": 12, "msg rcv total": 37701, "msg sent total": 39742}, "my-scheduler-6b748d4857-km75n": {"setup time": 125.500720289, "avg time per iter": 288261.23076923075, "total time": 3747396, "total iter": 12, "msg rcv total": 43225, "msg sent total": 36421}, "my-scheduler-6b748d4857-km9m7": {"setup time": 84.782626618, "avg time per iter": 279793.8461538461, "total time": 3637320, "total iter": 12, "msg rcv total": 40002, "msg sent total": 33005}, "my-scheduler-6b748d4857-kn9lf": {"setup time": 100.619823518, "avg time per iter": 278768.46153846156, "total time": 3623990, "total iter": 12, "msg rcv total": 39324, "msg sent total": 31727}, "my-scheduler-6b748d4857-kpjqj": {"setup time": 133.443575007, "avg time per iter": 290119.23076923075, "total time": 3771550, "total iter": 12, "msg rcv total": 40565, "msg sent total": 32310}, "my-scheduler-6b748d4857-ksslx": {"setup time": 120.836229, "avg time per iter": 288029, "total time": 3744377, "total iter": 12, "msg rcv total": 41230, "msg sent total": 41776}, "my-scheduler-6b748d4857-kvcn4": {"setup time": 81.965395941, "avg time per iter": 281613.46153846156, "total time": 3660975, "total iter": 12, "msg rcv total": 37968, "msg sent total": 39833}, "my-scheduler-6b748d4857-kwfbx": {"setup time": 118.306819364, "avg time per iter": 285525.3076923077, "total time": 3711829, "total iter": 12, "msg rcv total": 33250, "msg sent total": 45805}, "my-scheduler-6b748d4857-kxjcl": {"setup time": 93.315871438, "avg time per iter": 273182.92307692306, "total time": 3551378, "total iter": 12, "msg rcv total": 34578, "msg sent total": 47226}, "my-scheduler-6b748d4857-kz6d8": {"setup time": 84.001334786, "avg time per iter": 278830.23076923075, "total time": 3624793, "total iter": 12, "msg rcv total": 37968, "msg sent total": 47191}, "my-scheduler-6b748d4857-l4tsb": {"setup time": 107.817507057, "avg time per iter": 283244.76923076925, "total time": 3682182, "total iter": 12, "msg rcv total": 37290, "msg sent total": 39103}, "my-scheduler-6b748d4857-l5v7f": {"setup time": 129.870898612, "avg time per iter": 289943.92307692306, "total time": 3769271, "total iter": 12, "msg rcv total": 41895, "msg sent total": 35661}, "my-scheduler-6b748d4857-l6nqc": {"setup time": 129.095334242, "avg time per iter": 289136.8461538461, "total time": 3758779, "total iter": 12, "msg rcv total": 43225, "msg sent total": 39768}, "my-scheduler-6b748d4857-l6rtb": {"setup time": 78.322480841, "avg time per iter": 277406.8461538461, "total time": 3606289, "total iter": 12, "msg rcv total": 44748, "msg sent total": 32936}, "my-scheduler-6b748d4857-l72vh": {"setup time": 77.627470274, "avg time per iter": 278155.3076923077, "total time": 3616019, "total iter": 12, "msg rcv total": 34578, "msg sent total": 38438}, "my-scheduler-6b748d4857-l7zzl": {"setup time": 111.02219789, "avg time per iter": 284510.3846153846, "total time": 3698635, "total iter": 12, "msg rcv total": 38646, "msg sent total": 36326}, "my-scheduler-6b748d4857-l9d25": {"setup time": 71.055174334, "avg time per iter": 277748.46153846156, "total time": 3610730, "total iter": 12, "msg rcv total": 42036, "msg sent total": 43106}, "my-scheduler-6b748d4857-lbh7l": {"setup time": 84.060954494, "avg time per iter": 278341, "total time": 3618433, "total iter": 12, "msg rcv total": 41358, "msg sent total": 50486}, "my-scheduler-6b748d4857-lbwmd": {"setup time": 87.438007156, "avg time per iter": 277131.1538461539, "total time": 3602705, "total iter": 12, "msg rcv total": 43392, "msg sent total": 47204}, "my-scheduler-6b748d4857-lcd2n": {"setup time": 133.773729063, "avg time per iter": 289877.3076923077, "total time": 3768405, "total iter": 12, "msg rcv total": 31255, "msg sent total": 34370}, "my-scheduler-6b748d4857-lcg9c": {"setup time": 93.20842497, "avg time per iter": 271972.07692307694, "total time": 3535637, "total iter": 12, "msg rcv total": 38646, "msg sent total": 37030}, "my-scheduler-6b748d4857-lhw9c": {"setup time": 88.057501824, "avg time per iter": 276949.76923076925, "total time": 3600347, "total iter": 12, "msg rcv total": 41358, "msg sent total": 35661}, "my-scheduler-6b748d4857-lmch5": {"setup time": 101.126223894, "avg time per iter": 278074.6153846154, "total time": 3614970, "total iter": 12, "msg rcv total": 38646, "msg sent total": 40355}, "my-scheduler-6b748d4857-ln8nj": {"setup time": 126.150879717, "avg time per iter": 288529.6923076923, "total time": 3750886, "total iter": 12, "msg rcv total": 49210, "msg sent total": 45883}, "my-scheduler-6b748d4857-lph2j": {"setup time": 112.413856731, "avg time per iter": 284002.07692307694, "total time": 3692027, "total iter": 12, "msg rcv total": 50540, "msg sent total": 33692}, "my-scheduler-6b748d4857-lrfpn": {"setup time": 92.737710945, "avg time per iter": 274059.6153846154, "total time": 3562775, "total iter": 12, "msg rcv total": 35934, "msg sent total": 42467}, "my-scheduler-6b748d4857-lwjpl": {"setup time": 86.109145905, "avg time per iter": 280566, "total time": 3647358, "total iter": 12, "msg rcv total": 35934, "msg sent total": 36365}, "my-scheduler-6b748d4857-lzh77": {"setup time": 122.818886522, "avg time per iter": 288548.6923076923, "total time": 3751133, "total iter": 12, "msg rcv total": 38570, "msg sent total": 46444}, "my-scheduler-6b748d4857-m2gjv": {"setup time": 88.608378221, "avg time per iter": 277035.07692307694, "total time": 3601456, "total iter": 12, "msg rcv total": 48816, "msg sent total": 47109}, "my-scheduler-6b748d4857-m42sx": {"setup time": 132.579080837, "avg time per iter": 290179.76923076925, "total time": 3772337, "total iter": 12, "msg rcv total": 42560, "msg sent total": 41815}, "my-scheduler-6b748d4857-m44td": {"setup time": 116.890697182, "avg time per iter": 287708.07692307694, "total time": 3740205, "total iter": 12, "msg rcv total": 40565, "msg sent total": 36991}, "my-scheduler-6b748d4857-m56bc": {"setup time": 89.191599798, "avg time per iter": 273500.3846153846, "total time": 3555505, "total iter": 12, "msg rcv total": 43392, "msg sent total": 43823}, "my-scheduler-6b748d4857-m59w4": {"setup time": 118.225454089, "avg time per iter": 285754.92307692306, "total time": 3714814, "total iter": 12, "msg rcv total": 37240, "msg sent total": 38425}, "my-scheduler-6b748d4857-m8lmf": {"setup time": 78.375101996, "avg time per iter": 276908.1538461539, "total time": 3599806, "total iter": 12, "msg rcv total": 36612, "msg sent total": 37747}, "my-scheduler-6b748d4857-mc7p4": {"setup time": 112.289999797, "avg time per iter": 284209.53846153844, "total time": 3694724, "total iter": 12, "msg rcv total": 40565, "msg sent total": 33614}, "my-scheduler-6b748d4857-mcklg": {"setup time": 132.28308542, "avg time per iter": 290563.8461538461, "total time": 3777330, "total iter": 12, "msg rcv total": 35245, "msg sent total": 41802}, "my-scheduler-6b748d4857-md955": {"setup time": 128.216957347, "avg time per iter": 288261.76923076925, "total time": 3747403, "total iter": 12, "msg rcv total": 42560, "msg sent total": 38425}, "my-scheduler-6b748d4857-mfzhj": {"setup time": 75.055898665, "avg time per iter": 278458, "total time": 3619954, "total iter": 12, "msg rcv total": 35934, "msg sent total": 43132}, "my-scheduler-6b748d4857-mg8df": {"setup time": 86.481648511, "avg time per iter": 280786.6923076923, "total time": 3650227, "total iter": 12, "msg rcv total": 44748, "msg sent total": 42402}, "my-scheduler-6b748d4857-mhpvf": {"setup time": 65.996498177, "avg time per iter": 283662.76923076925, "total time": 3687616, "total iter": 12, "msg rcv total": 44748, "msg sent total": 40446}, "my-scheduler-6b748d4857-mj22h": {"setup time": 115.167155354, "avg time per iter": 286806.6923076923, "total time": 3728487, "total iter": 12, "msg rcv total": 40565, "msg sent total": 39051}, "my-scheduler-6b748d4857-mjxkp": {"setup time": 65.402677221, "avg time per iter": 281717.92307692306, "total time": 3662333, "total iter": 12, "msg rcv total": 39324, "msg sent total": 34422}, "my-scheduler-6b748d4857-mps7w": {"setup time": 86.522191269, "avg time per iter": 279074.23076923075, "total time": 3627965, "total iter": 12, "msg rcv total": 37968, "msg sent total": 34409}, "my-scheduler-6b748d4857-mqk7q": {"setup time": 118.204141943, "avg time per iter": 286671.3846153846, "total time": 3726728, "total iter": 12, "msg rcv total": 37905, "msg sent total": 41059}, "my-scheduler-6b748d4857-mr29s": {"setup time": 81.437278362, "avg time per iter": 278956.07692307694, "total time": 3626429, "total iter": 12, "msg rcv total": 44748, "msg sent total": 42454}, "my-scheduler-6b748d4857-mv4vl": {"setup time": 117.563486597, "avg time per iter": 285009.8461538461, "total time": 3705128, "total iter": 12, "msg rcv total": 38570, "msg sent total": 34387}, "my-scheduler-6b748d4857-mxpjk": {"setup time": 117.539605, "avg time per iter": 288632.92307692306, "total time": 3752228, "total iter": 12, "msg rcv total": 31255, "msg sent total": 41737}, "my-scheduler-6b748d4857-n5p66": {"setup time": 94.523520076, "avg time per iter": 272343.1538461539, "total time": 3540461, "total iter": 12, "msg rcv total": 40680, "msg sent total": 44449}, "my-scheduler-6b748d4857-n6z99": {"setup time": 127.908455092, "avg time per iter": 289193, "total time": 3759509, "total iter": 12, "msg rcv total": 40565, "msg sent total": 35661}, "my-scheduler-6b748d4857-n947c": {"setup time": 112.984506867, "avg time per iter": 284839.23076923075, "total time": 3702910, "total iter": 12, "msg rcv total": 37905, "msg sent total": 40424}, "my-scheduler-6b748d4857-ngdrt": {"setup time": 79.146748942, "avg time per iter": 277773.1538461539, "total time": 3611051, "total iter": 12, "msg rcv total": 42036, "msg sent total": 44462}, "my-scheduler-6b748d4857-nj8b2": {"setup time": 83.889540142, "avg time per iter": 278188.46153846156, "total time": 3616450, "total iter": 12, "msg rcv total": 44748, "msg sent total": 37747}, "my-scheduler-6b748d4857-nnwn4": {"setup time": 91.627061276, "avg time per iter": 283719.46153846156, "total time": 3688353, "total iter": 12, "msg rcv total": 43392, "msg sent total": 42415}, "my-scheduler-6b748d4857-npszk": {"setup time": 114.624455652, "avg time per iter": 286603.76923076925, "total time": 3725849, "total iter": 12, "msg rcv total": 41895, "msg sent total": 38399}, "my-scheduler-6b748d4857-npvbt": {"setup time": 82.653791811, "avg time per iter": 278287.6923076923, "total time": 3617740, "total iter": 12, "msg rcv total": 40002, "msg sent total": 40472}, "my-scheduler-6b748d4857-ns4zl": {"setup time": 65.777003125, "avg time per iter": 283462.76923076925, "total time": 3685016, "total iter": 12, "msg rcv total": 42714, "msg sent total": 41789}, "my-scheduler-6b748d4857-nwkwf": {"setup time": 100.280383217, "avg time per iter": 278100, "total time": 3615300, "total iter": 12, "msg rcv total": 44748, "msg sent total": 41059}, "my-scheduler-6b748d4857-nwm8b": {"setup time": 118.717125121, "avg time per iter": 286111.6923076923, "total time": 3719452, "total iter": 12, "msg rcv total": 45885, "msg sent total": 36417}, "my-scheduler-6b748d4857-p49lp": {"setup time": 103.014687683, "avg time per iter": 278973.6923076923, "total time": 3626658, "total iter": 12, "msg rcv total": 38646, "msg sent total": 34305}, "my-scheduler-6b748d4857-p4hdx": {"setup time": 109.254272688, "avg time per iter": 273815.53846153844, "total time": 3559602, "total iter": 12, "msg rcv total": 49494, "msg sent total": 41098}, "my-scheduler-6b748d4857-p65xl": {"setup time": 70.472519075, "avg time per iter": 277444.3076923077, "total time": 3606776, "total iter": 12, "msg rcv total": 38646, "msg sent total": 40446}, "my-scheduler-6b748d4857-p7bpf": {"setup time": 129.543608479, "avg time per iter": 290276.07692307694, "total time": 3773589, "total iter": 12, "msg rcv total": 41230, "msg sent total": 35739}, "my-scheduler-6b748d4857-pcff2": {"setup time": 118.999669355, "avg time per iter": 286014.07692307694, "total time": 3718183, "total iter": 12, "msg rcv total": 45220, "msg sent total": 35687}, "my-scheduler-6b748d4857-pchq4": {"setup time": 91.185305202, "avg time per iter": 283337.76923076925, "total time": 3683391, "total iter": 12, "msg rcv total": 42036, "msg sent total": 41650}, "my-scheduler-6b748d4857-pcj7t": {"setup time": 127.473278169, "avg time per iter": 289059.3846153846, "total time": 3757772, "total iter": 12, "msg rcv total": 45885, "msg sent total": 35022}, "my-scheduler-6b748d4857-pfwdg": {"setup time": 108.634078508, "avg time per iter": 274524.46153846156, "total time": 3568818, "total iter": 12, "msg rcv total": 45426, "msg sent total": 45870}, "my-scheduler-6b748d4857-pgjd9": {"setup time": 98.515169193, "avg time per iter": 277331, "total time": 3605303, "total iter": 12, "msg rcv total": 44070, "msg sent total": 36326}, "my-scheduler-6b748d4857-pjk9b": {"setup time": 117.628843359, "avg time per iter": 287278.46153846156, "total time": 3734620, "total iter": 12, "msg rcv total": 36575, "msg sent total": 44436}, "my-scheduler-6b748d4857-ppzx8": {"setup time": 103.208400638, "avg time per iter": 274337, "total time": 3566381, "total iter": 12, "msg rcv total": 44070, "msg sent total": 47904}, "my-scheduler-6b748d4857-pt9w7": {"setup time": 113.607215353, "avg time per iter": 285896.46153846156, "total time": 3716654, "total iter": 12, "msg rcv total": 43225, "msg sent total": 31006}, "my-scheduler-6b748d4857-pwg7q": {"setup time": 105.430002033, "avg time per iter": 274934.8461538461, "total time": 3574153, "total iter": 12, "msg rcv total": 39324, "msg sent total": 36404}, "my-scheduler-6b748d4857-q22q5": {"setup time": 70.388780352, "avg time per iter": 276213.07692307694, "total time": 3590770, "total iter": 12, "msg rcv total": 37290, "msg sent total": 35687}, "my-scheduler-6b748d4857-q7cn9": {"setup time": 97.286196853, "avg time per iter": 274424, "total time": 3567512, "total iter": 12, "msg rcv total": 41358, "msg sent total": 46405}, "my-scheduler-6b748d4857-q8frd": {"setup time": 76.327727253, "avg time per iter": 279640.23076923075, "total time": 3635323, "total iter": 12, "msg rcv total": 41358, "msg sent total": 41767}, "my-scheduler-6b748d4857-q9fxs": {"setup time": 99.332627653, "avg time per iter": 277172.46153846156, "total time": 3603242, "total iter": 12, "msg rcv total": 33222, "msg sent total": 37695}, "my-scheduler-6b748d4857-qcq5p": {"setup time": 103.224189305, "avg time per iter": 279176.6153846154, "total time": 3629296, "total iter": 12, "msg rcv total": 36612, "msg sent total": 47930}, "my-scheduler-6b748d4857-qd7rp": {"setup time": 118.577108034, "avg time per iter": 287467.53846153844, "total time": 3737078, "total iter": 12, "msg rcv total": 29925, "msg sent total": 35022}, "my-scheduler-6b748d4857-qdwqp": {"setup time": 87.996881507, "avg time per iter": 282870.3076923077, "total time": 3677314, "total iter": 12, "msg rcv total": 43392, "msg sent total": 39129}, "my-scheduler-6b748d4857-qgvd2": {"setup time": 105.788864815, "avg time per iter": 282706.3076923077, "total time": 3675182, "total iter": 12, "msg rcv total": 38646, "msg sent total": 40420}, "my-scheduler-6b748d4857-qhq9c": {"setup time": 108.347095308, "avg time per iter": 284122.6153846154, "total time": 3693594, "total iter": 12, "msg rcv total": 34578, "msg sent total": 42467}, "my-scheduler-6b748d4857-qhzkc": {"setup time": 126.895370473, "avg time per iter": 289164.07692307694, "total time": 3759133, "total iter": 12, "msg rcv total": 45220, "msg sent total": 35648}, "my-scheduler-6b748d4857-qlbdn": {"setup time": 95.972380629, "avg time per iter": 275536.76923076925, "total time": 3581978, "total iter": 12, "msg rcv total": 50172, "msg sent total": 36378}, "my-scheduler-6b748d4857-qsfzj": {"setup time": 88.311679455, "avg time per iter": 281114.92307692306, "total time": 3654494, "total iter": 12, "msg rcv total": 40002, "msg sent total": 37043}, "my-scheduler-6b748d4857-qtd8f": {"setup time": 109.079316714, "avg time per iter": 273340.46153846156, "total time": 3553426, "total iter": 12, "msg rcv total": 46104, "msg sent total": 44462}, "my-scheduler-6b748d4857-qvmvg": {"setup time": 113.590426067, "avg time per iter": 284250.1538461539, "total time": 3695252, "total iter": 12, "msg rcv total": 41895, "msg sent total": 34370}, "my-scheduler-6b748d4857-r7mtm": {"setup time": 92.015125936, "avg time per iter": 278248.1538461539, "total time": 3617226, "total iter": 12, "msg rcv total": 44748, "msg sent total": 41085}, "my-scheduler-6b748d4857-r8kmr": {"setup time": 68.919544976, "avg time per iter": 283233.3846153846, "total time": 3682034, "total iter": 12, "msg rcv total": 43392, "msg sent total": 40420}, "my-scheduler-6b748d4857-r8p5j": {"setup time": 113.70043213, "avg time per iter": 283722.76923076925, "total time": 3688396, "total iter": 12, "msg rcv total": 38570, "msg sent total": 37017}, "my-scheduler-6b748d4857-r9rtq": {"setup time": 96.645514895, "avg time per iter": 272954.07692307694, "total time": 3548403, "total iter": 12, "msg rcv total": 43392, "msg sent total": 51125}, "my-scheduler-6b748d4857-rbgdr": {"setup time": 111.827029484, "avg time per iter": 284899.6923076923, "total time": 3703696, "total iter": 12, "msg rcv total": 35934, "msg sent total": 36417}, "my-scheduler-6b748d4857-rmpcq": {"setup time": 109.018082251, "avg time per iter": 283078.23076923075, "total time": 3680017, "total iter": 12, "msg rcv total": 40002, "msg sent total": 39742}, "my-scheduler-6b748d4857-rn6b6": {"setup time": 76.218703025, "avg time per iter": 277194.6923076923, "total time": 3603531, "total iter": 12, "msg rcv total": 42036, "msg sent total": 40433}, "my-scheduler-6b748d4857-rnf4d": {"setup time": 100.985079388, "avg time per iter": 273385.3846153846, "total time": 3554010, "total iter": 12, "msg rcv total": 37290, "msg sent total": 38986}, "my-scheduler-6b748d4857-rnkdx": {"setup time": 120.624962775, "avg time per iter": 282871.3076923077, "total time": 3677327, "total iter": 12, "msg rcv total": 39900, "msg sent total": 37712}, "my-scheduler-6b748d4857-rqbk7": {"setup time": 88.665262273, "avg time per iter": 276885, "total time": 3599505, "total iter": 12, "msg rcv total": 40680, "msg sent total": 35048}, "my-scheduler-6b748d4857-rrksw": {"setup time": 78.915308338, "avg time per iter": 278352.76923076925, "total time": 3618586, "total iter": 12, "msg rcv total": 48816, "msg sent total": 37069}, "my-scheduler-6b748d4857-rs89k": {"setup time": 121.420932782, "avg time per iter": 286754.23076923075, "total time": 3727805, "total iter": 12, "msg rcv total": 49875, "msg sent total": 39155}, "my-scheduler-6b748d4857-s2k9v": {"setup time": 123.910064113, "avg time per iter": 287603.6153846154, "total time": 3738847, "total iter": 12, "msg rcv total": 42560, "msg sent total": 38399}, "my-scheduler-6b748d4857-s87g6": {"setup time": 93.927733896, "avg time per iter": 272933.92307692306, "total time": 3548141, "total iter": 12, "msg rcv total": 43392, "msg sent total": 41189}, "my-scheduler-6b748d4857-sbzfz": {"setup time": 120.539090972, "avg time per iter": 287301, "total time": 3734913, "total iter": 12, "msg rcv total": 40565, "msg sent total": 39742}, "my-scheduler-6b748d4857-scbxl": {"setup time": 91.904853495, "avg time per iter": 276508.92307692306, "total time": 3594616, "total iter": 12, "msg rcv total": 36612, "msg sent total": 49899}, "my-scheduler-6b748d4857-scwjr": {"setup time": 90.704211396, "avg time per iter": 275974.53846153844, "total time": 3587669, "total iter": 12, "msg rcv total": 44748, "msg sent total": 41033}, "my-scheduler-6b748d4857-sczfg": {"setup time": 97.73385725, "avg time per iter": 274630.3846153846, "total time": 3570195, "total iter": 12, "msg rcv total": 42036, "msg sent total": 37669}, "my-scheduler-6b748d4857-shrk6": {"setup time": 112.180869865, "avg time per iter": 284060.3846153846, "total time": 3692785, "total iter": 12, "msg rcv total": 37968, "msg sent total": 38412}, "my-scheduler-6b748d4857-swvqf": {"setup time": 99.792200245, "avg time per iter": 278175.07692307694, "total time": 3616276, "total iter": 12, "msg rcv total": 35934, "msg sent total": 45062}, "my-scheduler-6b748d4857-szf8d": {"setup time": 100.66568758, "avg time per iter": 275369.8461538461, "total time": 3579808, "total iter": 12, "msg rcv total": 35256, "msg sent total": 45114}, "my-scheduler-6b748d4857-t5266": {"setup time": 79.66535298, "avg time per iter": 278407.3846153846, "total time": 3619296, "total iter": 12, "msg rcv total": 35934, "msg sent total": 41750}, "my-scheduler-6b748d4857-t6w22": {"setup time": 126.220289935, "avg time per iter": 288704, "total time": 3753152, "total iter": 12, "msg rcv total": 46550, "msg sent total": 41767}, "my-scheduler-6b748d4857-t997b": {"setup time": 121.590854072, "avg time per iter": 288619.23076923075, "total time": 3752050, "total iter": 12, "msg rcv total": 40565, "msg sent total": 43823}, "my-scheduler-6b748d4857-tcvqj": {"setup time": 94.910089175, "avg time per iter": 242092.6923076923, "total time": 3147205, "total iter": 12, "msg rcv total": 37968, "msg sent total": 43171}, "my-scheduler-6b748d4857-tfqv6": {"setup time": 99.857630099, "avg time per iter": 278003.6153846154, "total time": 3614047, "total iter": 12, "msg rcv total": 38646, "msg sent total": 41111}, "my-scheduler-6b748d4857-tgwqg": {"setup time": 73.186203115, "avg time per iter": 259692.61538461538, "total time": 3376004, "total iter": 12, "msg rcv total": 52206, "msg sent total": 48543}, "my-scheduler-6b748d4857-thq6z": {"setup time": 78.069583885, "avg time per iter": 281166.23076923075, "total time": 3655161, "total iter": 12, "msg rcv total": 38646, "msg sent total": 39038}, "my-scheduler-6b748d4857-tjdjk": {"setup time": 79.887988657, "avg time per iter": 277438.23076923075, "total time": 3606697, "total iter": 12, "msg rcv total": 38646, "msg sent total": 35700}, "my-scheduler-6b748d4857-tkmhb": {"setup time": 95.146717383, "avg time per iter": 273374.3846153846, "total time": 3553867, "total iter": 12, "msg rcv total": 32544, "msg sent total": 37056}, "my-scheduler-6b748d4857-tkq86": {"setup time": 110.499848744, "avg time per iter": 273226.92307692306, "total time": 3551950, "total iter": 12, "msg rcv total": 39324, "msg sent total": 45196}, "my-scheduler-6b748d4857-tp5ws": {"setup time": 116.003471184, "avg time per iter": 284242.46153846156, "total time": 3695152, "total iter": 12, "msg rcv total": 39900, "msg sent total": 36443}, "my-scheduler-6b748d4857-tpfz6": {"setup time": 107.0581762, "avg time per iter": 282917.76923076925, "total time": 3677931, "total iter": 12, "msg rcv total": 35256, "msg sent total": 51216}, "my-scheduler-6b748d4857-tv6t5": {"setup time": 121.866692172, "avg time per iter": 287948.76923076925, "total time": 3743334, "total iter": 12, "msg rcv total": 40565, "msg sent total": 37708}, "my-scheduler-6b748d4857-tvvrq": {"setup time": 118.595145004, "avg time per iter": 287205.6153846154, "total time": 3733673, "total iter": 12, "msg rcv total": 41895, "msg sent total": 35687}, "my-scheduler-6b748d4857-tz7wl": {"setup time": 117.395183546, "avg time per iter": 285534.07692307694, "total time": 3711943, "total iter": 12, "msg rcv total": 40565, "msg sent total": 37017}, "my-scheduler-6b748d4857-v2vn4": {"setup time": 96.307348305, "avg time per iter": 274978.8461538461, "total time": 3574725, "total iter": 12, "msg rcv total": 39324, "msg sent total": 43823}, "my-scheduler-6b748d4857-v2wz5": {"setup time": 81.024638848, "avg time per iter": 279151.3076923077, "total time": 3628967, "total iter": 12, "msg rcv total": 40002, "msg sent total": 40355}, "my-scheduler-6b748d4857-v45gp": {"setup time": 112.833727943, "avg time per iter": 285745.3846153846, "total time": 3714690, "total iter": 12, "msg rcv total": 37240, "msg sent total": 38464}, "my-scheduler-6b748d4857-v6zcp": {"setup time": 100.79182646, "avg time per iter": 272766.6153846154, "total time": 3545966, "total iter": 12, "msg rcv total": 41358, "msg sent total": 39690}, "my-scheduler-6b748d4857-v8qcn": {"setup time": 120.342200823, "avg time per iter": 285294.76923076925, "total time": 3708832, "total iter": 12, "msg rcv total": 40565, "msg sent total": 39742}, "my-scheduler-6b748d4857-vf5fp": {"setup time": 100.655920252, "avg time per iter": 273803, "total time": 3559439, "total iter": 12, "msg rcv total": 39324, "msg sent total": 43788}, "my-scheduler-6b748d4857-vfphj": {"setup time": 134.09425044, "avg time per iter": 288439.6923076923, "total time": 3749716, "total iter": 12, "msg rcv total": 35245, "msg sent total": 42441}, "my-scheduler-6b748d4857-vknc7": {"setup time": 82.534690081, "avg time per iter": 277534.23076923075, "total time": 3607945, "total iter": 12, "msg rcv total": 44070, "msg sent total": 37786}, "my-scheduler-6b748d4857-vmdg5": {"setup time": 112.988907041, "avg time per iter": 282238.07692307694, "total time": 3669095, "total iter": 12, "msg rcv total": 39235, "msg sent total": 39755}, "my-scheduler-6b748d4857-vqvll": {"setup time": 77.486322571, "avg time per iter": 280884.1538461539, "total time": 3651494, "total iter": 12, "msg rcv total": 40002, "msg sent total": 37734}, "my-scheduler-6b748d4857-vvv8x": {"setup time": 111.635025998, "avg time per iter": 282910, "total time": 3677830, "total iter": 12, "msg rcv total": 48138, "msg sent total": 38438}, "my-scheduler-6b748d4857-vxl28": {"setup time": 90.950482415, "avg time per iter": 283384.76923076925, "total time": 3684002, "total iter": 12, "msg rcv total": 43392, "msg sent total": 36339}, "my-scheduler-6b748d4857-w5cns": {"setup time": 84.634416952, "avg time per iter": 279914.23076923075, "total time": 3638885, "total iter": 12, "msg rcv total": 37290, "msg sent total": 43810}, "my-scheduler-6b748d4857-w5pnr": {"setup time": 110.345585546, "avg time per iter": 271783.1538461539, "total time": 3533181, "total iter": 12, "msg rcv total": 27120, "msg sent total": 37708}, "my-scheduler-6b748d4857-w6gmd": {"setup time": 102.573928284, "avg time per iter": 278912.3076923077, "total time": 3625860, "total iter": 12, "msg rcv total": 34578, "msg sent total": 37725}, "my-scheduler-6b748d4857-w8mpg": {"setup time": 68.989229306, "avg time per iter": 278489.92307692306, "total time": 3620369, "total iter": 12, "msg rcv total": 40680, "msg sent total": 41163}, "my-scheduler-6b748d4857-w9fpb": {"setup time": 87.950360158, "avg time per iter": 275272.53846153844, "total time": 3578543, "total iter": 12, "msg rcv total": 32544, "msg sent total": 35687}, "my-scheduler-6b748d4857-wb74t": {"setup time": 116.348207621, "avg time per iter": 285075.1538461539, "total time": 3705977, "total iter": 12, "msg rcv total": 40565, "msg sent total": 40407}, "my-scheduler-6b748d4857-wcffh": {"setup time": 105.589953112, "avg time per iter": 274357.6153846154, "total time": 3566649, "total iter": 12, "msg rcv total": 42036, "msg sent total": 41033}, "my-scheduler-6b748d4857-wd9zk": {"setup time": 93.443172481, "avg time per iter": 273003.07692307694, "total time": 3549040, "total iter": 12, "msg rcv total": 39324, "msg sent total": 40381}, "my-scheduler-6b748d4857-whkjn": {"setup time": 85.974755231, "avg time per iter": 278149.3076923077, "total time": 3615941, "total iter": 12, "msg rcv total": 44070, "msg sent total": 37056}, "my-scheduler-6b748d4857-whq5k": {"setup time": 83.568964682, "avg time per iter": 278584.3846153846, "total time": 3621597, "total iter": 12, "msg rcv total": 44748, "msg sent total": 41672}, "my-scheduler-6b748d4857-whrff": {"setup time": 86.747013784, "avg time per iter": 277669.6153846154, "total time": 3609705, "total iter": 12, "msg rcv total": 40680, "msg sent total": 40498}, "my-scheduler-6b748d4857-wrd4d": {"setup time": 82.15920355, "avg time per iter": 277555.76923076925, "total time": 3608225, "total iter": 12, "msg rcv total": 36612, "msg sent total": 32949}, "my-scheduler-6b748d4857-wrp2v": {"setup time": 107.303119427, "avg time per iter": 273552.07692307694, "total time": 3556177, "total iter": 12, "msg rcv total": 38646, "msg sent total": 42506}, "my-scheduler-6b748d4857-wx5j6": {"setup time": 108.037051127, "avg time per iter": 257930.46153846153, "total time": 3353096, "total iter": 12, "msg rcv total": 41358, "msg sent total": 35713}, "my-scheduler-6b748d4857-x2c67": {"setup time": 83.468960994, "avg time per iter": 278301.6923076923, "total time": 3617922, "total iter": 12, "msg rcv total": 37290, "msg sent total": 42419}, "my-scheduler-6b748d4857-x2f2q": {"setup time": 92.725659175, "avg time per iter": 273432.3846153846, "total time": 3554621, "total iter": 12, "msg rcv total": 38646, "msg sent total": 45062}, "my-scheduler-6b748d4857-x4gtm": {"setup time": 76.928765893, "avg time per iter": 277507.92307692306, "total time": 3607603, "total iter": 12, "msg rcv total": 41358, "msg sent total": 41711}, "my-scheduler-6b748d4857-x4khl": {"setup time": 76.961358755, "avg time per iter": 280077.23076923075, "total time": 3641004, "total iter": 12, "msg rcv total": 41358, "msg sent total": 41085}, "my-scheduler-6b748d4857-x5dht": {"setup time": 101.930050717, "avg time per iter": 274920.3846153846, "total time": 3573965, "total iter": 12, "msg rcv total": 49494, "msg sent total": 41806}, "my-scheduler-6b748d4857-x6mjq": {"setup time": 67.645009185, "avg time per iter": 282468.07692307694, "total time": 3672085, "total iter": 12, "msg rcv total": 42036, "msg sent total": 36434}, "my-scheduler-6b748d4857-x6vqb": {"setup time": 127.214348796, "avg time per iter": 287855.76923076925, "total time": 3742125, "total iter": 12, "msg rcv total": 35245, "msg sent total": 37108}, "my-scheduler-6b748d4857-x7h7b": {"setup time": 103.244495014, "avg time per iter": 280316.1538461539, "total time": 3644110, "total iter": 12, "msg rcv total": 27798, "msg sent total": 38399}, "my-scheduler-6b748d4857-x8v4p": {"setup time": 90.06847483, "avg time per iter": 277735.53846153844, "total time": 3610562, "total iter": 12, "msg rcv total": 42036, "msg sent total": 43810}, "my-scheduler-6b748d4857-xbnx8": {"setup time": 125.96905076, "avg time per iter": 288552.3846153846, "total time": 3751181, "total iter": 12, "msg rcv total": 38570, "msg sent total": 41867}, "my-scheduler-6b748d4857-xc5mg": {"setup time": 101.818560111, "avg time per iter": 274971.92307692306, "total time": 3574635, "total iter": 12, "msg rcv total": 38646, "msg sent total": 50590}, "my-scheduler-6b748d4857-xfs74": {"setup time": 67.000196475, "avg time per iter": 283918.53846153844, "total time": 3690941, "total iter": 12, "msg rcv total": 29832, "msg sent total": 46509}, "my-scheduler-6b748d4857-xk484": {"setup time": 105.115782545, "avg time per iter": 281837.46153846156, "total time": 3663887, "total iter": 12, "msg rcv total": 41358, "msg sent total": 34396}, "my-scheduler-6b748d4857-xmtsz": {"setup time": 115.666594444, "avg time per iter": 284785.1538461539, "total time": 3702207, "total iter": 12, "msg rcv total": 37240, "msg sent total": 45805}, "my-scheduler-6b748d4857-xpbqg": {"setup time": 91.856099585, "avg time per iter": 284365.23076923075, "total time": 3696748, "total iter": 12, "msg rcv total": 40680, "msg sent total": 42558}, "my-scheduler-6b748d4857-xphs9": {"setup time": 104.407344521, "avg time per iter": 281531.8461538461, "total time": 3659914, "total iter": 12, "msg rcv total": 41358, "msg sent total": 46470}, "my-scheduler-6b748d4857-xspc8": {"setup time": 69.059068683, "avg time per iter": 276356.76923076925, "total time": 3592638, "total iter": 12, "msg rcv total": 42036, "msg sent total": 36952}, "my-scheduler-6b748d4857-xtmhn": {"setup time": 72.018251177, "avg time per iter": 276602.6153846154, "total time": 3595834, "total iter": 12, "msg rcv total": 41358, "msg sent total": 41754}, "my-scheduler-6b748d4857-xvv4r": {"setup time": 130.754235316, "avg time per iter": 288966, "total time": 3756558, "total iter": 12, "msg rcv total": 39900, "msg sent total": 43810}, "my-scheduler-6b748d4857-xx2w6": {"setup time": 96.561904668, "avg time per iter": 275802, "total time": 3585426, "total iter": 12, "msg rcv total": 42036, "msg sent total": 47878}, "my-scheduler-6b748d4857-xxdjd": {"setup time": 123.991796873, "avg time per iter": 288814.8461538461, "total time": 3754593, "total iter": 12, "msg rcv total": 43225, "msg sent total": 42493}, "my-scheduler-6b748d4857-xxj75": {"setup time": 96.486962892, "avg time per iter": 274260.92307692306, "total time": 3565392, "total iter": 12, "msg rcv total": 40002, "msg sent total": 49199}, "my-scheduler-6b748d4857-xz7k7": {"setup time": 82.573862964, "avg time per iter": 277981.3846153846, "total time": 3613758, "total iter": 12, "msg rcv total": 42714, "msg sent total": 47752}, "my-scheduler-6b748d4857-xz944": {"setup time": 87.78345314, "avg time per iter": 280719.6923076923, "total time": 3649356, "total iter": 12, "msg rcv total": 38646, "msg sent total": 45792}, "my-scheduler-6b748d4857-xznp2": {"setup time": 91.422028681, "avg time per iter": 278340.53846153844, "total time": 3618427, "total iter": 12, "msg rcv total": 35934, "msg sent total": 33066}, "my-scheduler-6b748d4857-zck99": {"setup time": 97.175099597, "avg time per iter": 274459.6923076923, "total time": 3567976, "total iter": 12, "msg rcv total": 43392, "msg sent total": 41098}, "my-scheduler-6b748d4857-zd54d": {"setup time": 101.762943992, "avg time per iter": 278630.6923076923, "total time": 3622199, "total iter": 12, "msg rcv total": 37968, "msg sent total": 39081}, "my-scheduler-6b748d4857-zf6fw": {"setup time": 83.333274991, "avg time per iter": 278648, "total time": 3622424, "total iter": 12, "msg rcv total": 40680, "msg sent total": 40472}, "my-scheduler-6b748d4857-zg5w9": {"setup time": 95.214308537, "avg time per iter": 276116.53846153844, "total time": 3589515, "total iter": 12, "msg rcv total": 33900, "msg sent total": 36313}, "my-scheduler-6b748d4857-zgrsc": {"setup time": 110.891541399, "avg time per iter": 285457.1538461539, "total time": 3710943, "total iter": 12, "msg rcv total": 50172, "msg sent total": 41711}, "my-scheduler-6b748d4857-zht7h": {"setup time": 103.862199869, "avg time per iter": 274135.46153846156, "total time": 3563761, "total iter": 12, "msg rcv total": 34578, "msg sent total": 33027}, "my-scheduler-6b748d4857-zlbkt": {"setup time": 134.338031297, "avg time per iter": 286978.3846153846, "total time": 3730719, "total iter": 12, "msg rcv total": 40565, "msg sent total": 41020}, "my-scheduler-6b748d4857-zm9qc": {"setup time": 80.975487032, "avg time per iter": 279256.46153846156, "total time": 3630334, "total iter": 12, "msg rcv total": 35256, "msg sent total": 42480}, "my-scheduler-6b748d4857-znz5d": {"setup time": 69.705025094, "avg time per iter": 277784.6153846154, "total time": 3611200, "total iter": 12, "msg rcv total": 36612, "msg sent total": 39742}, "my-scheduler-6b748d4857-zqnlz": {"setup time": 93.257464322, "avg time per iter": 273252.6923076923, "total time": 3552285, "total iter": 12, "msg rcv total": 42036, "msg sent total": 45796}, "my-scheduler-6b748d4857-zsvp4": {"setup time": 91.246200704, "avg time per iter": 283845.3076923077, "total time": 3689989, "total iter": 12, "msg rcv total": 37290, "msg sent total": 36978}, "my-scheduler-6b748d4857-zvsh8": {"setup time": 105.631836777, "avg time per iter": 274469.3076923077, "total time": 3568101, "total iter": 12, "msg rcv total": 32544, "msg sent total": 39716}, "my-scheduler-6b748d4857-zvtfd": {"setup time": 92.632119002, "avg time per iter": 272716.6153846154, "total time": 3545316, "total iter": 12, "msg rcv total": 38646, "msg sent total": 38386}, "my-scheduler-6b748d4857-zzgz5": {"setup time": 76.816703284, "avg time per iter": 280034.1538461539, "total time": 3640444, "total iter": 12, "msg rcv total": 46782, "msg sent total": 53198}}}
